{
	"Type": "Generic",
	"GUID": "C5887CCE63457CD417BD95A56EB5922F",
	"Name": "initiative",
	"Metadata": "",
	"CollisionType": "Regular",
	"Friction": 0.7,
	"Restitution": 0.3,
	"Density": 1,
	"SurfaceType": "Wood",
	"Roughness": 0.4,
	"Metallic": 1,
	"PrimaryColor":
	{
		"R": 221,
		"G": 221,
		"B": 221
	},
	"SecondaryColor":
	{
		"R": 0,
		"G": 0,
		"B": 0
	},
	"Flippable": false,
	"AutoStraighten": true,
	"ShouldSnap": true,
	"ScriptName": "initiative-marker.js",
	"Blueprint": "",
	"Models": [
		{
			"Model": "initiative.obj",
			"Offset":
			{
				"X": 0,
				"Y": 0,
				"Z": 0
			},
			"Scale":
			{
				"X": 1,
				"Y": 1,
				"Z": 1
			},
			"Rotation":
			{
				"X": 0,
				"Y": 0,
				"Z": 0
			},
			"Texture": "wood-texture.jpg",
			"NormalMap": "wood-texture-n.jpg",
			"ExtraMap": "",
			"ExtraMap2": "",
			"IsTransparent": false,
			"CastShadow": true,
			"IsTwoSided": false,
			"UseOverrides": true,
			"SurfaceType": "Plastic"
		}
	],
	"Collision": [],
	"Lights": [],
	"SnapPointsGlobal": false,
	"SnapPoints": [],
	"ZoomViewDirection":
	{
		"X": 0,
		"Y": 0,
		"Z": 0
	},
	"GroundAccessibility": "Nothing",
	"Tags": []
}