{
	"Type": "Generic",
	"GUID": "6B48B3A29446CC831C4965BE1B4E1F3E",
	"Name": "player",
	"Metadata": "",
	"CollisionType": "Ground",
	"Friction": 0.7,
	"Restitution": 0.3,
	"Density": 1,
	"SurfaceType": "Wood",
	"Roughness": 1,
	"Metallic": 0,
	"PrimaryColor":
	{
		"R": 255,
		"G": 255,
		"B": 255
	},
	"SecondaryColor":
	{
		"R": 0,
		"G": 0,
		"B": 0
	},
	"Flippable": false,
	"AutoStraighten": false,
	"ShouldSnap": true,
	"ScriptName": "",
	"Blueprint": "Blueprints/Board.json",
	"Models": [
		{
			"Model": "StaticMesh'/Game/Meshes/Generic/BoardSurface.BoardSurface'",
			"Offset":
			{
				"X": 0,
				"Y": 0,
				"Z": 0
			},
			"Scale":
			{
				"X": 0.26034444410247098,
				"Y": 0.64997901388216139,
				"Z": 0.99996772512655496
			},
			"Rotation":
			{
				"X": -0,
				"Y": 0,
				"Z": 0
			},
			"Texture": "playerboard.jpg",
			"NormalMap": "",
			"ExtraMap": "playerboard mask.jpg",
			"ExtraMap2": "",
			"IsTransparent": false,
			"CastShadow": true,
			"IsTwoSided": false,
			"UseOverrides": true,
			"SurfaceType": "Plastic"
		}
	],
	"Collision": [],
	"Lights": [],
	"SnapPointsGlobal": false,
	"SnapPoints": [
		{
			"X": 2.6000000000000001,
			"Y": -10.438000000000001,
			"Z": 0.5,
			"Range": 2,
			"SnapRotation": 2,
			"RotationOffset": 0,
			"Shape": 0,
			"FlipValidity": 0,
			"Tags": [
				"resource"
			]
		},
		{
			"X": 2.6000000000000001,
			"Y": -7.4380000000000006,
			"Z": 0.5,
			"Range": 2,
			"SnapRotation": 2,
			"RotationOffset": 0,
			"Shape": 0,
			"FlipValidity": 0,
			"Tags": [
				"resource"
			]
		},
		{
			"X": 2.7999999999999998,
			"Y": 10.635,
			"Z": 0.5,
			"Range": 2,
			"SnapRotation": 2,
			"RotationOffset": 0,
			"Shape": 0,
			"FlipValidity": 0,
			"Tags": [
				"building"
			]
		},
		{
			"X": 2.7999999999999998,
			"Y": 7.5960000000000001,
			"Z": 0.5,
			"Range": 2,
			"SnapRotation": 2,
			"RotationOffset": 0,
			"Shape": 0,
			"FlipValidity": 0,
			"Tags": [
				"building"
			]
		},
		{
			"X": 2.7999999999999998,
			"Y": 3.0800000000000001,
			"Z": 0.5,
			"Range": 2,
			"SnapRotation": 2,
			"RotationOffset": 0,
			"Shape": 0,
			"FlipValidity": 0,
			"Tags": [
				"building"
			]
		},
		{
			"X": 2.7999999999999998,
			"Y": -1.427,
			"Z": 0.5,
			"Range": 2,
			"SnapRotation": 2,
			"RotationOffset": 0,
			"Shape": 0,
			"FlipValidity": 0,
			"Tags": [
				"building"
			]
		},
		{
			"X": 2.7999999999999998,
			"Y": -4.4438000000000004,
			"Z": 0.5,
			"Range": 2,
			"SnapRotation": 2,
			"RotationOffset": 0,
			"Shape": 0,
			"FlipValidity": 0,
			"Tags": [
				"building"
			]
		},
		{
			"X": 2.6000000000000001,
			"Y": -4.4380000000000006,
			"Z": 0.5,
			"Range": 2,
			"SnapRotation": 2,
			"RotationOffset": 0,
			"Shape": 0,
			"FlipValidity": 0,
			"Tags": [
				"resource"
			]
		},
		{
			"X": 2.6000000000000001,
			"Y": -1.4380000000000002,
			"Z": 0.5,
			"Range": 2,
			"SnapRotation": 2,
			"RotationOffset": 0,
			"Shape": 0,
			"FlipValidity": 0,
			"Tags": [
				"resource"
			]
		},
		{
			"X": 2.6000000000000001,
			"Y": 1.5619999999999998,
			"Z": 0.5,
			"Range": 2,
			"SnapRotation": 2,
			"RotationOffset": 0,
			"Shape": 0,
			"FlipValidity": 0,
			"Tags": [
				"resource"
			]
		},
		{
			"X": 2.6000000000000001,
			"Y": 4.5619999999999994,
			"Z": 0.5,
			"Range": 2,
			"SnapRotation": 2,
			"RotationOffset": 0,
			"Shape": 0,
			"FlipValidity": 0,
			"Tags": [
				"resource"
			]
		},
		{
			"X": -4.1900000000000004,
			"Y": -7,
			"Z": 0.5,
			"Range": 1,
			"SnapRotation": 2,
			"RotationOffset": 0,
			"Shape": 0,
			"FlipValidity": 0,
			"Tags": [
				"agent"
			]
		},
		{
			"X": -3.0899999999999999,
			"Y": -7,
			"Z": 0.5,
			"Range": 1,
			"SnapRotation": 2,
			"RotationOffset": 0,
			"Shape": 0,
			"FlipValidity": 0,
			"Tags": [
				"agent"
			]
		},
		{
			"X": -1.99,
			"Y": -7,
			"Z": 0.5,
			"Range": 1,
			"SnapRotation": 2,
			"RotationOffset": 0,
			"Shape": 0,
			"FlipValidity": 0,
			"Tags": [
				"agent"
			]
		},
		{
			"X": -0.89000000000000001,
			"Y": -7,
			"Z": 0.5,
			"Range": 1,
			"SnapRotation": 2,
			"RotationOffset": 0,
			"Shape": 0,
			"FlipValidity": 0,
			"Tags": [
				"agent"
			]
		},
		{
			"X": 0.20999999999999999,
			"Y": -7,
			"Z": 0.5,
			"Range": 1,
			"SnapRotation": 2,
			"RotationOffset": 0,
			"Shape": 0,
			"FlipValidity": 0,
			"Tags": [
				"agent"
			]
		}
	],
	"ZoomViewDirection":
	{
		"X": 0,
		"Y": 0,
		"Z": 0
	},
	"GroundAccessibility": "Nothing",
	"Tags": []
}